<annotation>
	<folder>pubg plane</folder>
	<filename>32.31f-eSMQHZL._UY395_.jpg</filename>
	<path>/Users/Royaltchan/Downloads/PUBG/pubg plane/32.31f-eSMQHZL._UY395_.jpg</path>
	<source>
		<database>Unknown</database>
	</source>
	<size>
		<width>395</width>
		<height>395</height>
		<depth>3</depth>
	</size>
	<segmented>0</segmented>
	<object>
		<name>Plane</name>
		<pose>Unspecified</pose>
		<truncated>0</truncated>
		<difficult>0</difficult>
		<bndbox>
			<xmin>110</xmin>
			<ymin>90</ymin>
			<xmax>327</xmax>
			<ymax>369</ymax>
		</bndbox>
	</object>
</annotation>
