<annotation>
	<folder>pubg vehicle</folder>
	<filename>69.Capture.jpg</filename>
	<path>/Users/Royaltchan/Downloads/PUBG/pubg vehicle/69.Capture.jpg</path>
	<source>
		<database>Unknown</database>
	</source>
	<size>
		<width>648</width>
		<height>625</height>
		<depth>3</depth>
	</size>
	<segmented>0</segmented>
	<object>
		<name>Player</name>
		<pose>Unspecified</pose>
		<truncated>0</truncated>
		<difficult>0</difficult>
		<bndbox>
			<xmin>59</xmin>
			<ymin>88</ymin>
			<xmax>280</xmax>
			<ymax>592</ymax>
		</bndbox>
	</object>
	<object>
		<name>Vehicle</name>
		<pose>Unspecified</pose>
		<truncated>0</truncated>
		<difficult>0</difficult>
		<bndbox>
			<xmin>56</xmin>
			<ymin>174</ymin>
			<xmax>611</xmax>
			<ymax>577</ymax>
		</bndbox>
	</object>
</annotation>
